{
  "posts": [
    {
      "title": "2025-03-07-15ultra",
      "date": "",
      "tags": [],
      "filename": "2025-03-07-15ultra.html"
    },
    {
      "title": "2025-03-07-咧气王",
      "date": "",
      "tags": [],
      "filename": "2025-03-07-咧气王.html"
    },
    {
      "title": "2025-03-07-我去了",
      "date": "",
      "tags": [],
      "filename": "2025-03-07-我去了.html"
    },
    {
      "title": "2025-03-08-ahaha",
      "date": "",
      "tags": [],
      "filename": "2025-03-08-ahaha.html"
    },
    {
      "title": "2025-03-08-从百草园到三味书屋",
      "date": "",
      "tags": [],
      "filename": "2025-03-08-从百草园到三味书屋.html"
    },
    {
      "title": "2025-03-08-山东炒鸡王",
      "date": "",
      "tags": [],
      "filename": "2025-03-08-山东炒鸡王.html"
    },
    {
      "title": "2025-03-08-最新文章",
      "date": "",
      "tags": [],
      "filename": "2025-03-08-最新文章.html"
    }
  ],
  "generated_at": "2025-03-08"
}